pyraider/__init__.py
pyraider/cli.py
pyraider/main_pyraider.py
pyraider/utils.py
tests/__init__.py
tests/test_pyraider.py
pyraider-1.0.20.dist-info/LICENSE
pyraider-1.0.20.dist-info/METADATA
pyraider-1.0.20.dist-info/WHEEL
pyraider-1.0.20.dist-info/entry_points.txt
pyraider-1.0.20.dist-info/top_level.txt
pyraider-1.0.20.dist-info/RECORD
