Metadata-Version: 2.1
Name: pyraider
Version: 1.0.20
Summary: Using PyRaider You can scan installed dependencies known security vulnerabilities. It uses publicly known exploits, vulnerabilities database.
Home-page: https://github.com/tilakthimmappa/pyraider
Author: Tilak Thimmappa
Author-email: tilakthimmappa@gmail.com
License: UNKNOWN
Keywords: SCA,pyraider,Source Composition Analysis,vulnerability scanner
Platform: UNKNOWN
Classifier: Programming Language :: Python :: 3
Classifier: License :: OSI Approved :: MIT License
Classifier: Operating System :: OS Independent
Requires-Python: >=3
Requires-Dist: docopt
Requires-Dist: beautifultable
Requires-Dist: colored
Requires-Dist: json2html
